hhoppe_tools/__init__.py
hhoppe_tools/py.typed
hhoppe_tools-1.6.0.dist-info/licenses/LICENSE
hhoppe_tools-1.6.0.dist-info/WHEEL
hhoppe_tools-1.6.0.dist-info/METADATA
hhoppe_tools-1.6.0.dist-info/RECORD
