Metadata-Version: 2.4
Name: hhoppe-tools
Version: 1.6.0
Summary: Library of Python tools by Hugues Hoppe
Keywords: 
Author-email: Hugues Hoppe <hhoppe@gmail.com>
Requires-Python: >=3.9
Classifier: License :: OSI Approved :: MIT License
Classifier: Operating System :: OS Independent
Classifier: Programming Language :: Python :: 3
Classifier: Topic :: Software Development :: Libraries :: Python Modules
License-File: LICENSE
Requires-Dist: numpy
Requires-Dist: matplotlib ; extra == "dev"
Requires-Dist: pdoc ; extra == "dev"
Requires-Dist: Pillow ; extra == "dev"
Requires-Dist: IPython ; extra == "dev"
Project-URL: homepage, https://github.com/hhoppe/hhoppe-tools
Project-URL: repository, https://github.com/hhoppe/hhoppe-tools
Provides-Extra: dev
